[
    {
        "Time": "08:00",
        "Activity": "Log in to the OA system, check emails, and prepare for meetings scheduled for the day."
    },
    {
        "Time": "09:00",
        "Activity": "Meet with @his-1 and @his-2 to discuss health informatics integration strategies."
    },
    {
        "Time": "10:30",
        "Activity": "Review feedback from training sessions conducted by @trainer-1 and compile necessary improvements."
    },
    {
        "Time": "12:00",
        "Activity": "Lunch break."
    },
    {
        "Time": "14:00",
        "Activity": "Continue working on implementing enhancements for the EHR system based on user feedback."
    },
    {
        "Time": "16:00",
        "Activity": "Conduct a quality assurance test on the new enhancements with @qatest-2."
    },
    {
        "Time": "17:00",
        "Activity": "Check for any unanswered emails and respond accordingly."
    }
]