[
    {
        "Time": "08:00",
        "Activity": "Log in to the system, check emails, and make note of any urgent issues raised."
    },
    {
        "Time": "09:00",
        "Activity": "Attend a strategy planning meeting with @itpm-1 for upcoming milestones in the EHR project."
    },
    {
        "Time": "10:00",
        "Activity": "Consult @ehrv-1 for updates on the vendor's roadmap for EHR improvements."
    },
    {
        "Time": "11:00",
        "Activity": "Share insights on seasonal influenza trends with @da-1 and @da-2 to enhance data relevant to the EHR."
    },
    {
        "Time": "14:00",
        "Activity": "Host a training session with @trainer-1 to guide staff on using new EHR features effectively."
    },
    {
        "Time": "15:00",
        "Activity": "Review user feedback collected through @helpdesk-1 regarding EHR functionalities and address concerns."
    },
    {
        "Time": "16:00",
        "Activity": "Prepare for a summary report with highlighted achievements and ongoing challenges for EHR integration."
    },
    {
        "Time": "17:00",
        "Activity": "Finalize the report and send it to all stakeholders for transparency on project status."
    }
]