[
    {
        "Time": "08:00",
        "Activity": "Check emails and respond to any follow-ups from @pm-1 or @comp-1 regarding the compliance report."
    },
    {
        "Time": "09:00",
        "Activity": "Finalize the compliance report and send it to @comp-1 for final review and approval."
    },
    {
        "Time": "10:00",
        "Activity": "Begin preparing the monthly financial statements using the finalized template and data from @qres-3."
    },
    {
        "Time": "11:00",
        "Activity": "Cross-check financial data with @cio-1 to ensure accuracy and consistency."
    },
    {
        "Time": "12:00",
        "Activity": "Lunch break."
    },
    {
        "Time": "14:00",
        "Activity": "Complete the monthly financial statements and prepare them for review by @coo-1."
    },
    {
        "Time": "15:00",
        "Activity": "Email @coo-1 with the draft financial statements and request feedback or approval."
    },
    {
        "Time": "16:00",
        "Activity": "Organize all documents and files related to the week's tasks, ensuring everything is properly archived."
    },
    {
        "Time": "17:00",
        "Activity": "Prepare a summary of the week's accomplishments and any pending tasks for Friday."
    }
]