[
    {
        "Time": "08:00",
        "Activity": "Log in to the OA system, check emails. Review existing accounting procedures and identify gaps in tracking financial transactions."
    },
    {
        "Time": "09:00",
        "Activity": "Meet with @comp-1 to discuss compliance requirements for financial transaction tracking."
    },
    {
        "Time": "10:00",
        "Activity": "Draft a preliminary outline for accounting procedures, focusing on transaction tracking and compliance."
    },
    {
        "Time": "11:00",
        "Activity": "Research best practices for fund accounting procedures in hedge funds."
    },
    {
        "Time": "12:00",
        "Activity": "Lunch break."
    },
    {
        "Time": "14:00",
        "Activity": "Continue drafting accounting procedures, incorporating feedback from @comp-1."
    },
    {
        "Time": "15:00",
        "Activity": "Meet with @facc-2 to align on the accounting procedures draft."
    },
    {
        "Time": "16:00",
        "Activity": "Review and finalize the accounting procedures document."
    },
    {
        "Time": "17:00",
        "Activity": "Send the finalized accounting procedures to @coo-1 for approval."
    }
]