[
    {
        "Time": "08:00",
        "Activity": "Finalize the integration of all systems into a cohesive prototype."
    },
    {
        "Time": "10:00",
        "Activity": "Test the prototype internally to identify any remaining issues or inconsistencies."
    },
    {
        "Time": "12:00",
        "Activity": "Lunch break."
    },
    {
        "Time": "14:00",
        "Activity": "Prepare detailed documentation for handoff to Client Developers, including system interactions and known issues."
    },
    {
        "Time": "16:00",
        "Activity": "Email @cdev-3 and @sdev-1 to schedule a handoff meeting for the documentation."
    }
]