[
    {
        "Time": "08:00",
        "Activity": "Log in to the accounting system, check emails, and review any updates related to the financial accounting processes for the fund."
    },
    {
        "Time": "09:00",
        "Activity": "Meet with @facc-2 to discuss the current state of financial accounting processes and identify initial requirements for establishing processes for the fund."
    },
    {
        "Time": "10:00",
        "Activity": "Draft the outline for the initial financial accounting processes, focusing on transaction recording, reporting, and compliance tasks."
    },
    {
        "Time": "11:00",
        "Activity": "Send the draft outline of financial accounting processes to @comp-1 for feedback regarding compliance with SEC regulations."
    },
    {
        "Time": "12:00",
        "Activity": "Lunch break."
    },
    {
        "Time": "14:00",
        "Activity": "Start researching best practices for fund accounting processes by reviewing industry literature and resources."
    },
    {
        "Time": "15:00",
        "Activity": "Compile a list of necessary financial reporting tools and resources needed for fund accounting."
    },
    {
        "Time": "16:00",
        "Activity": "Discuss initial findings with @qres-1 to ensure the processes align with the quantitative analysis needs."
    },
    {
        "Time": "17:00",
        "Activity": "Review the day's work, update notes, and prepare for tomorrow's tasks."
    }
]