[
    {
        "Time": "08:00",
        "Activity": "Log in to the OA system, check emails, and prepare for final stakeholder presentation."
    },
    {
        "Time": "09:00",
        "Activity": "Draft presentation slides based on the updated prototypes and action plan."
    },
    {
        "Time": "11:00",
        "Activity": "Send the presentation draft to @pm-1 for feedback and approval."
    },
    {
        "Time": "12:00",
        "Activity": "Lunch break."
    },
    {
        "Time": "14:00",
        "Activity": "Present the updated software prototypes to the stakeholders, including @qres-1, @qres-2, @qres-3."
    },
    {
        "Time": "16:00",
        "Activity": "Discuss any last-minute feedback and decide on next steps."
    },
    {
        "Time": "17:00",
        "Activity": "Document the agreed actions based on stakeholder feedback from the presentation."
    }
]